torchinsight/__init__.py
torchinsight/formatter.py
torchinsight/model_info.py
torchinsight/utils.py
torchinsight/version.py
torchinsight-0.1.1.dist-info/licenses/LICENSE
torchinsight-0.1.1.dist-info/METADATA
torchinsight-0.1.1.dist-info/WHEEL
torchinsight-0.1.1.dist-info/top_level.txt
torchinsight-0.1.1.dist-info/RECORD
