Metadata-Version: 2.4
Name: torchinsight
Version: 0.1.1
Summary: Enhanced model analysis tool for PyTorch models
Home-page: https://github.com/Serendipity-zyf/torchinsight
Author: PixelCookie
Author-email: PixelCookie <metazyf@gmail.com>
License: MIT
Project-URL: Homepage, https://github.com/Serendipity-zyf/torchinsight
Project-URL: Bug Tracker, https://github.com/Serendipity-zyf/torchinsight/issues
Keywords: pytorch,deep-learning,model-analysis,visualization
Classifier: Development Status :: 3 - Alpha
Classifier: Intended Audience :: Developers
Classifier: Intended Audience :: Science/Research
Classifier: License :: OSI Approved :: MIT License
Classifier: Programming Language :: Python :: 3
Classifier: Programming Language :: Python :: 3.7
Classifier: Programming Language :: Python :: 3.8
Classifier: Programming Language :: Python :: 3.9
Classifier: Programming Language :: Python :: 3.10
Classifier: Topic :: Scientific/Engineering
Classifier: Topic :: Scientific/Engineering :: Artificial Intelligence
Requires-Python: >=3.7
License-File: LICENSE
Requires-Dist: torch>=1.7.0
Requires-Dist: colorama>=0.4.4
Dynamic: author
Dynamic: home-page
Dynamic: license-file
Dynamic: requires-python
